victo/__init__.py
victo/c_ds.py
victo/cproxy.py
victo/facade.py
victo/py_ds.py
victo/lib/linux/libvicto.so
victo/lib/macos/libvicto.dylib
victo-0.0.19.data/data/victo/lib/linux/libvicto.so
victo-0.0.19.data/data/victo/lib/macos/libvicto.dylib
victo-0.0.19.dist-info/LICENSE
victo-0.0.19.dist-info/METADATA
victo-0.0.19.dist-info/WHEEL
victo-0.0.19.dist-info/top_level.txt
victo-0.0.19.dist-info/RECORD
