Metadata-Version: 2.1
Name: victo
Version: 0.0.19
Summary: Victo - a vector database
Author: Sree Hari
Author-email: hari.tinyblitz@gmail.com
Classifier: Programming Language :: Python :: 3
Classifier: License :: OSI Approved :: MIT License
Classifier: Operating System :: MacOS
Requires-Python: >=3.6
License-File: LICENSE
